aptly_api/__init__.py
aptly_api/base.py
aptly_api/client.py
aptly_api/parts/__init__.py
aptly_api/parts/files.py
aptly_api/parts/mirrors.py
aptly_api/parts/misc.py
aptly_api/parts/packages.py
aptly_api/parts/publish.py
aptly_api/parts/repos.py
aptly_api/parts/snapshots.py
aptly_api_client-0.3.0.dist-info/LICENSE
aptly_api_client-0.3.0.dist-info/METADATA
aptly_api_client-0.3.0.dist-info/WHEEL
aptly_api_client-0.3.0.dist-info/top_level.txt
aptly_api_client-0.3.0.dist-info/RECORD
