Metadata-Version: 2.1
Name: aptly-api-client
Version: 0.3.0
Summary: A Python 3 client for the Aptly API
Author: Jonas Maurus (@jdelic)
Author-email: jonas@gopythongo.com
Maintainer: GoPythonGo.com
Maintainer-email: info@gopythongo.com
Classifier: Development Status :: 4 - Beta
Classifier: Intended Audience :: Developers
Classifier: Intended Audience :: System Administrators
Classifier: Environment :: Console
Classifier: Programming Language :: Python :: 3 :: Only
Classifier: License :: OSI Approved :: Mozilla Public License 2.0 (MPL 2.0)
Classifier: Operating System :: POSIX
License-File: LICENSE
Requires-Dist: requests
Requires-Dist: iso8601
